market_api/__init__.py
market_api/categories/__init__.py
market_api/categories/account.py
market_api/categories/base.py
market_api/categories/history.py
market_api/categories/items.py
market_api/categories/orders.py
market_api/categories/prices.py
market_api/categories/trades.py
market_api/categories/wss.py
market_api/client.py
market_api/const.py
market_api/exceptions.py
market_api/models/__init__.py
market_api/models/account.py
market_api/models/base.py
market_api/models/config.py
market_api/models/enum.py
market_api/models/history.py
market_api/models/items.py
market_api/models/orders.py
market_api/models/prices.py
market_api/models/trades.py
market_api/models/wss.py
market_api-1.0.0.dist-info/LICENSE
market_api-1.0.0.dist-info/WHEEL
market_api-1.0.0.dist-info/METADATA
market_api-1.0.0.dist-info/RECORD
