Metadata-Version: 2.1
Name: market-api
Version: 1.0.0
Summary: market.csgo.com api v2 wrapper
Home-page: https://github.com/lordralinc/market_api
License: MIT
Keywords: csgo_market,market,api
Author: lordralinc
Author-email: lordralinc@gmail.com
Requires-Python: >=3.8,<4.0
Classifier: License :: OSI Approved :: MIT License
Classifier: Programming Language :: Python :: 3
Classifier: Programming Language :: Python :: 3.8
Classifier: Programming Language :: Python :: 3.9
Classifier: Programming Language :: Python :: 3.10
Classifier: Programming Language :: Python :: 3.11
Requires-Dist: aenum (>=3.1.11,<4.0.0)
Requires-Dist: aiohttp (>=3.8.3,<4.0.0)
Requires-Dist: orjson (>=3.8.3,<4.0.0)
Requires-Dist: pydantic (>=1.10.2,<2.0.0)
Requires-Dist: toml (>=0.10.2,<0.11.0)
Project-URL: Repository, https://github.com/lordralinc/market_api
